<?xml version="1.0" encoding="utf-8"?>
<LanguageData>
  <!--The following translations were generated by https://www.deepl.com/-->
  <!-- EN: bad music -->
  <BadMusic.stages.bad_music.label>плохая музыка</BadMusic.stages.bad_music.label>
  <!-- EN: This is just noise, it makes me hate the very idea of music. -->
  <BadMusic.stages.bad_music.description>Это просто шум, он заставляет меня ненавидеть саму идею музыки.</BadMusic.stages.bad_music.description>
  <!-- EN: great music -->
  <GreatMusic.stages.great_music.label>прекрасная музыка</GreatMusic.stages.great_music.label>
  <!-- EN: This music is beautiful, it lets me forget my worries. -->
  <GreatMusic.stages.great_music.description>Эта музыка прекрасна, она позволяет мне забыть о своих заботах.</GreatMusic.stages.great_music.description>
  <!-- EN: nice music -->
  <NiceMusic.stages.nice_music.label>приятная музыка</NiceMusic.stages.nice_music.label>
  <!-- EN: Some music helps the colony feel more alive. -->
  <NiceMusic.stages.nice_music.description>Некоторая музыка помогает колонии чувствовать себя более живой.</NiceMusic.stages.nice_music.description>
</LanguageData>
